[{"postID":"CQM0yEoHvsj","videoUrl":"https://instagram.frec15-1.fna.fbcdn.net/v/t50.2886-16/201489613_623251265266284_6730197115903537669_n.mp4?_nc_ht=instagram.frec15-1.fna.fbcdn.net&_nc_cat=100&_nc_ohc=CanbkuQEOMMAX_WZAOa&edm=ABfd0MgBAAAA&ccb=7-4&oe=60CDD697&oh=53de3f0174f118435dba8ea6feb2cc4c&_nc_sid=7bff83","accountID":"videos_engracados2k"},{"postID":"CQL0wANnyko","videoUrl":"https://instagram.frec15-1.fna.fbcdn.net/v/t50.2886-16/200930843_394893345151164_7189608456485559407_n.mp4?_nc_ht=instagram.frec15-1.fna.fbcdn.net&_nc_cat=100&_nc_ohc=cOLa0bm1WjYAX9vfg0V&tn=KhuuXTvA9-Nqvc9j&edm=ABfd0MgBAAAA&ccb=7-4&oe=60CDCEF9&oh=016e3081cd45baf34a25a024de78c583&_nc_sid=7bff83","accountID":"videos_engracados2k"},{"postID":"CQJSH6YHoEY","videoUrl":"https://instagram.frec15-1.fna.fbcdn.net/v/t50.2886-16/202119772_223810426034894_4119481513784072707_n.mp4?_nc_ht=instagram.frec15-1.fna.fbcdn.net&_nc_cat=102&_nc_ohc=tZp0zgc8ttoAX_pU4oB&edm=ABfd0MgBAAAA&ccb=7-4&oe=60CD897F&oh=5303dc1a780eda55376cf823e2cd9d10&_nc_sid=7bff83","accountID":"videos_engracados2k"},{"postID":"CQILUQZn41O","videoUrl":"https://instagram.frec15-1.fna.fbcdn.net/v/t50.2886-16/131308168_528522588502789_7389653291494812379_n.mp4?_nc_ht=instagram.frec15-1.fna.fbcdn.net&_nc_cat=101&_nc_ohc=6QOHHZetzzEAX8tD4tg&tn=KhuuXTvA9-Nqvc9j&edm=ABfd0MgBAAAA&ccb=7-4&oe=60CDBFA3&oh=76fc2912a72a6cf7bc677e71e14da3f3&_nc_sid=7bff83","accountID":"videos_engracados2k"},{"postID":"CQE8NMfHnUw","videoUrl":"https://instagram.frec15-1.fna.fbcdn.net/v/t50.2886-16/131369487_2706864099611104_7727774220301169618_n.mp4?_nc_ht=instagram.frec15-1.fna.fbcdn.net&_nc_cat=104&_nc_ohc=wSb85UNdk1IAX9kNrx3&edm=ABfd0MgBAAAA&ccb=7-4&oe=60CDAD5B&oh=b56433388328c0a58bad3b83e1ca8f26&_nc_sid=7bff83","accountID":"videos_engracados2k"},{"postID":"CQE7xhtn1E9","videoUrl":"https://instagram.frec15-1.fna.fbcdn.net/v/t50.2886-16/201958893_794699447900333_5042264051590339056_n.mp4?_nc_ht=instagram.frec15-1.fna.fbcdn.net&_nc_cat=105&_nc_ohc=ZSYwpY2cnzkAX-4HiGg&tn=KhuuXTvA9-Nqvc9j&edm=ABfd0MgBAAAA&ccb=7-4&oe=60CD86FB&oh=ab51b982e34e2ec41d54c8ab5d35261b&_nc_sid=7bff83","accountID":"videos_engracados2k"},{"postID":"CQEGCxznc-K","videoUrl":"https://instagram.frec15-1.fna.fbcdn.net/v/t50.2886-16/201274618_799864187380413_4973070688102120546_n.mp4?_nc_ht=instagram.frec15-1.fna.fbcdn.net&_nc_cat=109&_nc_ohc=cVqCXEH8pIwAX-z6hY_&tn=KhuuXTvA9-Nqvc9j&edm=ABfd0MgBAAAA&ccb=7-4&oe=60CE0C62&oh=6115b6ecd2df17b1f63fd7367581b22f&_nc_sid=7bff83","accountID":"videos_engracados2k"},{"postID":"CQEFrUYnT8X","videoUrl":"https://instagram.frec15-1.fna.fbcdn.net/v/t50.2886-16/201855604_223284752755847_8836466995200493219_n.mp4?_nc_ht=instagram.frec15-1.fna.fbcdn.net&_nc_cat=111&_nc_ohc=L4QA_PD8lbEAX_m85JK&edm=ABfd0MgBAAAA&ccb=7-4&oe=60CDE3C8&oh=4e629d5f8bf1b66e59b172941cd03aab&_nc_sid=7bff83","accountID":"videos_engracados2k"},{"postID":"CQEFgqanhM5","videoUrl":"https://instagram.frec15-1.fna.fbcdn.net/v/t50.2886-16/200067083_810856329564330_710265210530957039_n.mp4?_nc_ht=instagram.frec15-1.fna.fbcdn.net&_nc_cat=106&_nc_ohc=h3lmNR8-zOsAX9G6W4e&tn=KhuuXTvA9-Nqvc9j&edm=ABfd0MgBAAAA&ccb=7-4&oe=60CDD2A7&oh=f6016d1b5659e5effc46085ac7933f1a&_nc_sid=7bff83","accountID":"videos_engracados2k"},{"postID":"CQC191GH6GZ","videoUrl":"https://instagram.frec15-1.fna.fbcdn.net/v/t50.2886-16/131339440_769793723708698_3266876015881789386_n.mp4?_nc_ht=instagram.frec15-1.fna.fbcdn.net&_nc_cat=110&_nc_ohc=OxLHVbcM9KAAX90zDi3&edm=ABfd0MgBAAAA&ccb=7-4&oe=60CE1C23&oh=0def76fd6aac3f9b76856e8135696da5&_nc_sid=7bff83","accountID":"videos_engracados2k"},{"postID":"CQOj4R6nC8L","videoUrl":"https://instagram.frec15-1.fna.fbcdn.net/v/t50.2886-16/201603404_477375103364758_9214648598599205625_n.mp4?_nc_ht=instagram.frec15-1.fna.fbcdn.net&_nc_cat=110&_nc_ohc=Hkh3ZgDt_w8AX-wGMey&edm=ABfd0MgBAAAA&ccb=7-4&oe=60CD91DB&oh=b0bd34c8beae115a8d0f3f63f7168e9a&_nc_sid=7bff83","accountID":"videospradarrisada"},{"postID":"CQL3IVjH6yB","videoUrl":"https://instagram.frec15-1.fna.fbcdn.net/v/t50.2886-16/201164614_481991546238367_3611289032605210651_n.mp4?_nc_ht=instagram.frec15-1.fna.fbcdn.net&_nc_cat=107&_nc_ohc=4gHbnWDLmqIAX90aVkV&tn=KhuuXTvA9-Nqvc9j&edm=ABfd0MgBAAAA&ccb=7-4&oe=60CDE636&oh=b05fc7b7667af08137e6bcf099530ab9&_nc_sid=7bff83","accountID":"videospradarrisada"},{"postID":"CQJ_EdiH4Hz","videoUrl":"https://instagram.frec15-1.fna.fbcdn.net/v/t50.2886-16/200868337_2850768468474142_5776505203081726485_n.mp4?_nc_ht=instagram.frec15-1.fna.fbcdn.net&_nc_cat=110&_nc_ohc=vDo-RYjC808AX8I0v3u&edm=ABfd0MgBAAAA&ccb=7-4&oe=60CDF218&oh=bd562c4ceaa39721884b4a7beb43b14b&_nc_sid=7bff83","accountID":"videospradarrisada"},{"postID":"CQJZ6svnKns","videoUrl":"https://instagram.frec15-1.fna.fbcdn.net/v/t50.2886-16/200790848_240914831132026_964910127775159194_n.mp4?_nc_ht=instagram.frec15-1.fna.fbcdn.net&_nc_cat=110&_nc_ohc=64ae_kc8DZcAX8my_TR&edm=ABfd0MgBAAAA&ccb=7-4&oe=60CD9BC1&oh=8f11d82d80b63e69a3f3605b29dfc4ab&_nc_sid=7bff83","accountID":"videospradarrisada"},{"postID":"CQHav-UnMn0","videoUrl":"https://instagram.frec15-1.fna.fbcdn.net/v/t50.2886-16/200643843_226421175739479_315170934286688866_n.mp4?_nc_ht=instagram.frec15-1.fna.fbcdn.net&_nc_cat=103&_nc_ohc=gx9WBATblMIAX8q0dZD&tn=KhuuXTvA9-Nqvc9j&edm=ABfd0MgBAAAA&ccb=7-4&oe=60CDC1BB&oh=45b7c24f05f6c3a87d8ef8c45a2b93af&_nc_sid=7bff83","accountID":"videospradarrisada"},{"postID":"CQG23_FnIq8","videoUrl":"https://instagram.frec15-1.fna.fbcdn.net/v/t50.2886-16/201162803_1471348466548700_8155883938508081468_n.mp4?_nc_ht=instagram.frec15-1.fna.fbcdn.net&_nc_cat=108&_nc_ohc=y4sn1lZm378AX9zwF95&tn=KhuuXTvA9-Nqvc9j&edm=ABfd0MgBAAAA&ccb=7-4&oe=60CDF57E&oh=3c9e94105ed269eeea6d29d74b7b42de&_nc_sid=7bff83","accountID":"videospradarrisada"},{"postID":"CQGuprIHhLT","videoUrl":"https://instagram.frec15-1.fna.fbcdn.net/v/t50.2886-16/201252383_148653133990806_5854248847330982342_n.mp4?_nc_ht=instagram.frec15-1.fna.fbcdn.net&_nc_cat=106&_nc_ohc=vFZJasV3VgYAX9ueBGN&tn=KhuuXTvA9-Nqvc9j&edm=ABfd0MgBAAAA&ccb=7-4&oe=60CD9F93&oh=ad3a199ccce95bfbfdb223218133abf6&_nc_sid=7bff83","accountID":"videospradarrisada"},{"postID":"CQE1_aznqLV","videoUrl":"https://instagram.frec15-1.fna.fbcdn.net/v/t50.2886-16/200278654_208240561032483_2228867281711013244_n.mp4?_nc_ht=instagram.frec15-1.fna.fbcdn.net&_nc_cat=103&_nc_ohc=ArPVo2LoowkAX8C6iIF&edm=ABfd0MgBAAAA&ccb=7-4&oe=60CDDF6A&oh=eae2d6f49365476b08143d334c663dd8&_nc_sid=7bff83","accountID":"videospradarrisada"},{"postID":"CQETSNzH_Rr","videoUrl":"https://instagram.frec15-1.fna.fbcdn.net/v/t50.2886-16/131284138_512061076786772_6472409521008722411_n.mp4?_nc_ht=instagram.frec15-1.fna.fbcdn.net&_nc_cat=108&_nc_ohc=YSvNYFLUwQwAX_f39f-&edm=ABfd0MgBAAAA&ccb=7-4&oe=60CDEBEE&oh=16df40708767ca372385652ab1265c2d&_nc_sid=7bff83","accountID":"videospradarrisada"},{"postID":"CQEJZ9nHLY1","videoUrl":"https://instagram.frec15-1.fna.fbcdn.net/v/t50.2886-16/201442589_915404845692254_51220436676392401_n.mp4?_nc_ht=instagram.frec15-1.fna.fbcdn.net&_nc_cat=102&_nc_ohc=NBMMfnCOcMcAX9abgx2&edm=ABfd0MgBAAAA&ccb=7-4&oe=60CE0424&oh=b5fd620daf4b685a72ae5b3c5045590a&_nc_sid=7bff83","accountID":"videospradarrisada"},{"postID":"CQLwNMngZVf","videoUrl":"https://instagram.frec15-1.fna.fbcdn.net/v/t50.2886-16/202925847_3749273118511331_126527411926155166_n.mp4?_nc_ht=instagram.frec15-1.fna.fbcdn.net&_nc_cat=111&_nc_ohc=pZS3ebc_y_4AX-JMPvI&tn=KhuuXTvA9-Nqvc9j&edm=ABfd0MgBAAAA&ccb=7-4&oe=60CE02F4&oh=6b7c5c60ad9b6109b64aca2d2022870b&_nc_sid=7bff83","accountID":"memes24horasoficial"},{"postID":"CQKbPyAg-RB","videoUrl":"https://instagram.frec15-1.fna.fbcdn.net/v/t50.2886-16/202147500_976917776184222_3610649152735243356_n.mp4?_nc_ht=instagram.frec15-1.fna.fbcdn.net&_nc_cat=106&_nc_ohc=4FZczGeDAAkAX9bSgVW&edm=ABfd0MgBAAAA&ccb=7-4&oe=60CDD54C&oh=597d47d75e562cc471f446163f769ae9&_nc_sid=7bff83","accountID":"memes24horasoficial"},{"postID":"CQJ4Sw9Awbd","videoUrl":"https://instagram.frec15-1.fna.fbcdn.net/v/t50.2886-16/202456720_337550991063362_1055587955527167717_n.mp4?_nc_ht=instagram.frec15-1.fna.fbcdn.net&_nc_cat=102&_nc_ohc=I2e_AApD-VEAX8BYzH_&tn=KhuuXTvA9-Nqvc9j&edm=ABfd0MgBAAAA&ccb=7-4&oe=60CDD965&oh=feec59f36def81507a9ff8fb44643fc7&_nc_sid=7bff83","accountID":"memes24horasoficial"},{"postID":"CQE21wtAqH7","videoUrl":"https://instagram.frec15-1.fna.fbcdn.net/v/t50.2886-16/201598983_333117934935492_5077058056440628406_n.mp4?_nc_ht=instagram.frec15-1.fna.fbcdn.net&_nc_cat=100&_nc_ohc=L4jvNl2rQOAAX-GgPDw&edm=ABfd0MgBAAAA&ccb=7-4&oe=60CDAEF3&oh=6b76e29b13e0356a8e3e57185ec2d626&_nc_sid=7bff83","accountID":"memes24horasoficial"},{"postID":"CQOdNcjlU5J","videoUrl":"https://instagram.frec15-1.fna.fbcdn.net/v/t50.2886-16/201452874_1186566095177257_1718850715620956665_n.mp4?_nc_ht=instagram.frec15-1.fna.fbcdn.net&_nc_cat=101&_nc_ohc=dNbdIAAd1UEAX-XIgXM&tn=KhuuXTvA9-Nqvc9j&edm=ABfd0MgBAAAA&ccb=7-4&oe=60CE12F9&oh=c11b126473ee9c4ed4fa99e1e2631a4c&_nc_sid=7bff83","accountID":"rindo.ate.2091"},{"postID":"CQM1M1oFNbD","videoUrl":"https://instagram.frec15-1.fna.fbcdn.net/v/t50.2886-16/201128678_155723256606239_5833410752219980313_n.mp4?_nc_ht=instagram.frec15-1.fna.fbcdn.net&_nc_cat=111&_nc_ohc=j02o2rZrDbwAX9W_wcE&tn=KhuuXTvA9-Nqvc9j&edm=ABfd0MgBAAAA&ccb=7-4&oe=60CDDDBC&oh=f79ca6aa64265a72d4b7116f5426d2b8&_nc_sid=7bff83","accountID":"rindo.ate.2091"},{"postID":"CQMf-1DFtYr","videoUrl":"https://instagram.frec15-1.fna.fbcdn.net/v/t50.2886-16/200044606_161586969218130_7287402915558728690_n.mp4?_nc_ht=instagram.frec15-1.fna.fbcdn.net&_nc_cat=106&_nc_ohc=cZHNfduLeF0AX842DW4&edm=ABfd0MgBAAAA&ccb=7-4&oe=60CE29ED&oh=73504368ad5be2ff38176e05fa806fe2&_nc_sid=7bff83","accountID":"rindo.ate.2091"},{"postID":"CQL29s-FJsN","videoUrl":"https://instagram.frec15-1.fna.fbcdn.net/v/t50.2886-16/201663980_818501812130800_2670837831664188458_n.mp4?_nc_ht=instagram.frec15-1.fna.fbcdn.net&_nc_cat=104&_nc_ohc=grzkiMhlBcMAX8eSpZE&edm=ABfd0MgBAAAA&ccb=7-4&oe=60CE1418&oh=3f13ec5f2a2f041fb382418700593690&_nc_sid=7bff83","accountID":"rindo.ate.2091"},{"postID":"CQKQnL-lx5N","videoUrl":"https://instagram.frec15-1.fna.fbcdn.net/v/t50.2886-16/131399000_949418742568605_3993526149949260318_n.mp4?_nc_ht=instagram.frec15-1.fna.fbcdn.net&_nc_cat=109&_nc_ohc=H-YC16tosaEAX_gP_JO&edm=ABfd0MgBAAAA&ccb=7-4&oe=60CD960D&oh=99590a98ee38b38a8df7abcaf8c1a68a&_nc_sid=7bff83","accountID":"rindo.ate.2091"},{"postID":"CQJTc_ileJE","videoUrl":"https://instagram.frec15-1.fna.fbcdn.net/v/t50.2886-16/200723907_1459023114460805_833741891658875819_n.mp4?_nc_ht=instagram.frec15-1.fna.fbcdn.net&_nc_cat=105&_nc_ohc=4haPqv-5WiMAX8ynFTP&edm=ABfd0MgBAAAA&ccb=7-4&oe=60CDEA59&oh=7c288927b6b53d07605ba53a5ed97c6a&_nc_sid=7bff83","accountID":"rindo.ate.2091"},{"postID":"CQHYi6XlgcZ","videoUrl":"https://instagram.frec15-1.fna.fbcdn.net/v/t50.2886-16/201383040_1416314105402908_4009854205174602060_n.mp4?_nc_ht=instagram.frec15-1.fna.fbcdn.net&_nc_cat=104&_nc_ohc=3sZ04WRYFpUAX90Dv4X&edm=ABfd0MgBAAAA&ccb=7-4&oe=60CDFFE8&oh=9d944a6b6453862883eb9520bf1c8086&_nc_sid=7bff83","accountID":"rindo.ate.2091"}]